MANIFEST.in
README.rst
setup.py
c/Makefile
c/README.md
c/Rules.mk
c/license.txt
c/custom/Makefile
c/custom/custom_code.bat
c/custom/main.c
c/custom/random.c
c/custom/random.h
c/include/curve25519_dh.h
c/include/ed25519_signature.h
c/include/external_calls.h
c/source/BaseTypes.h
c/source/Makefile
c/source/base_folding8.h
c/source/curve25519_dh.c
c/source/curve25519_mehdi.c
c/source/curve25519_mehdi.h
c/source/curve25519_order.c
c/source/curve25519_utils.c
c/source/custom_blind.c
c/source/ed25519_sign.c
c/source/ed25519_verify.c
c/source/sha512.c
c/source/sha512.h
c/source/asm64/Makefile
c/source/asm64/curve25519_mehdi_x64.c
c/source/asm64/curve25519_order_x64.c
c/source/asm64/curve25519_utils_x64.c
c/source/asm64/amd64.gnu/Add.s
c/source/asm64/amd64.gnu/Fold.s
c/source/asm64/amd64.gnu/Mult.s
c/source/asm64/amd64.gnu/Square.s
c/source/asm64/amd64.gnu/Sub.s
c/source/asm64/amd64.gnu/Tsc.s
c/source/asm64/amd64.gnu/WordMulAdd.s
c/source/asm64/amd64.gnu/defines.inc
c/source/asm64/amd64.masm/Add.asm
c/source/asm64/amd64.masm/Fold.asm
c/source/asm64/amd64.masm/Mult.asm
c/source/asm64/amd64.masm/Square.asm
c/source/asm64/amd64.masm/Sub.asm
c/source/asm64/amd64.masm/Tsc.asm
c/source/asm64/amd64.masm/WordMulAdd.asm
c/source/asm64/amd64.masm/defines.inc
c/test/Makefile
c/test/curve25519_donna.c
c/test/curve25519_donna.h
c/test/curve25519_selftest.c
c/test/curve25519_test.c
c/windows/EC25519.sln
c/windows/EC25519.vcxproj
c/windows/EC25519.vcxproj.filters
c/windows/EC25519.vcxproj.user
c/windows/Asm64Lib/Asm64Lib.vcxproj
c/windows/Asm64Lib/Asm64Lib.vcxproj.filters
c/windows/Asm64Lib/Asm64Lib.vcxproj.user
c/windows/Asm64Test/Asm64Test.vcxproj
c/windows/Asm64Test/Asm64Test.vcxproj.filters
c/windows/Asm64Test/Asm64Test.vcxproj.user
c/windows/Curve25519Lib/Curve25519Lib.vcxproj
c/windows/Curve25519Lib/Curve25519Lib.vcxproj.filters
c/windows/Curve25519Lib/Curve25519Lib.vcxproj.user
c/windows/CustomTool/CustomTool.vcxproj
c/windows/CustomTool/CustomTool.vcxproj.filters
prep/build.sh
py25519.egg-info/PKG-INFO
py25519.egg-info/SOURCES.txt
py25519.egg-info/dependency_links.txt
py25519.egg-info/requires.txt
py25519.egg-info/top_level.txt
py25519.egg-info/zip-safe
