Metadata-Version: 1.1
Name: py25519
Version: 0.13.28
Summary: py25519
Home-page: https://github.com/sundarnagarajan/py25519
Author: Sundar Nagarajan
Author-email: UNKNOWN
License: License :: OSI Approved :: MIT License
Download-URL: https://github.com/sundarnagarajan/py25519/tree/0.13.28
Platform: UNKNOWN
Classifier: Development Status :: 4 - Beta
Classifier: Programming Language :: Python :: 2
Classifier: Programming Language :: Python :: 3
Classifier: Programming Language :: Python :: Implementation :: PyPy
Classifier: License :: OSI Approved :: MIT License
Classifier: License :: OSI Approved :: GNU Lesser General Public License v3 or later (LGPLv3+)
